LICENSE
README.md
setup.py
pyenrichr/__init__.py
pyenrichr/enrichment.py
pyenrichr/libraries.py
pyenrichr/modules.py
pyenrichr.egg-info/PKG-INFO
pyenrichr.egg-info/SOURCES.txt
pyenrichr.egg-info/dependency_links.txt
pyenrichr.egg-info/requires.txt
pyenrichr.egg-info/top_level.txt
pyenrichr/data/ARCHS4_TFs_Coexp
pyenrichr/data/ChEA_2022
pyenrichr/data/DrugMatrix
pyenrichr/data/GO_Biological_Process_2023
pyenrichr/data/KEGG_2021_Human
pyenrichr/data/MGI_Mammalian_Phenotype_Level_4_2021
pyenrichr/data/WikiPathway_2023_Human
pyenrichr/data/config.json
pyenrichr/data/dbGaP
pyenrichr/data/example_gene_set.txt