Metadata-Version: 2.1
Name: pyenrichr
Version: 1.0.2
Summary: Official Enrichr Python package for fast local gene set enrichment.
Home-page: https://github.com/maayanlab/pyenrichr
Author: Alexander Lachmann
Author-email: alexander.lachmann@mssm.edu
Classifier: Programming Language :: Python :: 3
Classifier: License :: OSI Approved :: Apache Software License
Classifier: Operating System :: OS Independent
Requires-Python: >=3.6
License-File: LICENSE
Requires-Dist: pandas>=1.1.5
Requires-Dist: numpy
Requires-Dist: statsmodels
Requires-Dist: numba
Requires-Dist: python-louvain
Requires-Dist: networkx
Requires-Dist: tqdm
